{
    "timeToPourMetal": 12,
    "timeToDesulfOneLevel": 10,
    "timeToConvert": 13,
    "numOfSlotsAtFullBuffer": 10,
    "numOfSlotsAtDesulf": 3,
    "numOfSlotsAtConverter": 4,
    "timeToTransferFromEmptyBufferToFurnace": 2,
    "timeToTransferFromFurnaceToFullBuffer": 2,
    "timeToTransferFromFullBufferToDesulf": 2,
    "timeToTransferFromDesulfToConverter": 1,
    "timeToTransferFromConverterToEmptyBuffer": 5,
    "timeToEmergencyTransferFromFurnaceToEmptyBuffer": 11,
    "metalStartsPouringAt": [
        3,
        79,
        133,
        145,
        177,
        223,
        277,
        293,
        344,
        395,
        414,
        432,
        457,
        481,
        557,
        615,
        638,
        676,
        708,
        782,
        799,
        827,
        942,
        1026,
        1053,
        1092,
        1125,
        1149,
        1167,
        1220,
        1322,
        1336,
        1348,
        1378,
        1396,
        1415,
        1436,
        1475,
        1499,
        1559,
        1645,
        1678,
        1696,
        1737,
        1766,
        1780,
        1844,
        1864,
        1905,
        1947,
        1969,
        1984,
        2014,
        2048,
        2070,
        2089,
        2115,
        2131,
        2156,
        2170,
        2196,
        2222,
        2250,
        2281,
        2372,
        2399,
        2444,
        2476,
        2491,
        2556,
        2621,
        2663,
        2723,
        2748,
        2780,
        2825,
        2861,
        2876,
        2938,
        2955,
        3027,
        3100,
        3113,
        3170,
        3255,
        3300,
        3394,
        3414,
        3429,
        3486,
        3553,
        3617,
        3640,
        3654,
        3677,
        3711,
        3737,
        3806,
        3819,
        3833
    ],
    "metalSulfurLevels": [
        5,
        1,
        1,
        5,
        4,
        5,
        4,
        1,
        3,
        4,
        4,
        3,
        2,
        4,
        2,
        4,
        2,
        5,
        4,
        2,
        5,
        4,
        4,
        1,
        5,
        5,
        5,
        5,
        1,
        3,
        1,
        2,
        1,
        1,
        2,
        2,
        5,
        3,
        4,
        5,
        5,
        4,
        1,
        5,
        4,
        4,
        3,
        2,
        4,
        4,
        4,
        4,
        3,
        2,
        5,
        2,
        5,
        3,
        5,
        4,
        1,
        4,
        5,
        5,
        1,
        1,
        4,
        4,
        3,
        3,
        4,
        5,
        4,
        5,
        2,
        3,
        4,
        1,
        1,
        2,
        2,
        1,
        4,
        4,
        4,
        3,
        1,
        5,
        3,
        4,
        3,
        1,
        2,
        2,
        3,
        3,
        2,
        2,
        5,
        3
    ],
    "converterOpensAt": [
        50,
        96,
        240,
        310,
        449,
        451,
        474,
        632,
        725,
        809,
        844,
        1139,
        1395,
        1413,
        1432,
        1453,
        1512,
        1713,
        1715,
        1783,
        1861,
        1891,
        1994,
        2031,
        2106,
        2107,
        2148,
        2152,
        2187,
        2193,
        2213,
        2307,
        2389,
        2513,
        2518,
        2583,
        2700,
        2760,
        2805,
        2878,
        2893,
        3197,
        3272,
        3317,
        3456,
        3513,
        3634,
        3657,
        3738,
        3833
    ],
    "converterMaxSulfurLevels": [
        2,
        1,
        5,
        5,
        3,
        2,
        5,
        5,
        4,
        1,
        4,
        2,
        1,
        3,
        2,
        5,
        1,
        3,
        2,
        4,
        4,
        1,
        1,
        3,
        5,
        3,
        5,
        3,
        5,
        3,
        2,
        1,
        2,
        2,
        2,
        2,
        3,
        2,
        1,
        5,
        1,
        3,
        4,
        5,
        2,
        3,
        3,
        2,
        2,
        1
    ]
}